ascmii/__init__.py
ascmii/__main__.py
ascmii/__version__.py
ascmii/app.py
ascmii-0.0.2.dist-info/LICENSE
ascmii-0.0.2.dist-info/METADATA
ascmii-0.0.2.dist-info/WHEEL
ascmii-0.0.2.dist-info/entry_points.txt
ascmii-0.0.2.dist-info/top_level.txt
ascmii-0.0.2.dist-info/RECORD
