Metadata-Version: 2.1
Name: ascmii
Version: 0.0.2
Summary: ASCII Messenger
Home-page: https://github.com/lannocc/ascmii
Author: LANNOCC (Shawn A. Wilson)
Author-email: lannocc@yahoo.com
Classifier: Programming Language :: Python :: 3
Classifier: License :: OSI Approved :: MIT License
Classifier: Operating System :: OS Independent
License-File: LICENSE
Requires-Dist: appscii
Requires-Dist: lank
